README.rst
setup.py
dhp/__init__.py
dhp.egg-info/PKG-INFO
dhp.egg-info/SOURCES.txt
dhp.egg-info/dependency_links.txt
dhp.egg-info/top_level.txt
dhp/VI/__init__.py
dhp/cache/__init__.py
dhp/doq/__init__.py
dhp/math/__init__.py
dhp/search/__init__.py
dhp/structures/__init__.py
dhp/tempus/__init__.py
dhp/test/__init__.py
dhp/transforms/__init__.py
dhp/xml/__init__.py