Metadata-Version: 1.1
Name: dhp
Version: 0.0.13
Summary: A collection of handy modules, almost guaranteed to get you into trouble.
Home-page: https://bitbucket.org/dundeemt/dhp
Author: Jeff Hinrichs
Author-email: jeffh@dundeemt.com
License: BSD
Keywords: phrasebook hungarian
Platform: any
Classifier: Development Status :: 4 - Beta
Classifier: License :: OSI Approved :: BSD License
Classifier: Operating System :: OS Independent
Classifier: Programming Language :: Python
Classifier: Programming Language :: Python :: 2
Classifier: Programming Language :: Python :: 2.7
Classifier: Programming Language :: Python :: 3
Classifier: Programming Language :: Python :: 3.2
Classifier: Programming Language :: Python :: 3.3
Classifier: Programming Language :: Python :: 3.4
Classifier: Programming Language :: Python :: Implementation :: CPython
Classifier: Programming Language :: Python :: Implementation :: PyPy
